{"cameraMode":{"drawMode":0,"name":"Shaded","section":"Shading Mode"},"sceneLighting":true,"audioPlay":false,"sceneViewState":{"m_AlwaysRefresh":false,"showFog":true,"showSkybox":true,"showFlares":true,"showImageEffects":true,"showParticleSystems":true,"showVisualEffectGraphs":true,"m_FxEnabled":true},"in2DMode":false,"pivot":{"x":-16.0881404876709,"y":5.186112403869629,"z":1.6097643375396729},"rotation":{"x":-0.16402341425418855,"y":-0.2676490247249603,"z":0.0466344840824604,"w":-0.9486122727394104},"size":3.1718242168426515,"orthographic":false}